[
    {
        "title": "A Demographic Perspective of Smartphone Security and Its Redesigned Notifications",
        "pub_year": "2019",
        "citation": "情報処理学会論文誌 60 (12), 2019",
        "num_citations": 0,
        "author_pub_id": "tRmAOagAAAAJ:hqOjcs7Dif8C"
    },
    {
        "title": "A Game or Notes? The Use of a Customized Mobile Game to Improve Teenagers’ Phishing Knowledge, Case of Tanzania",
        "pub_year": "2022",
        "citation": "Journal of Cybersecurity and Privacy 2 (3), 466-489, 2022",
        "num_citations": 3,
        "author_pub_id": "tRmAOagAAAAJ:dhFuZR0502QC"
    },
    {
        "title": "A comparative study of smartphone-user security perception and preference towards redesigned security notifications",
        "pub_year": "2018",
        "citation": "Proceedings of the Second African Conference for Human Computer Interaction …, 2018",
        "num_citations": 8,
        "author_pub_id": "tRmAOagAAAAJ:zYLM7Y9cAGgC"
    },
    {
        "title": "A demographic perspective of smartphone security and its redesigned notifications",
        "pub_year": "2019",
        "citation": "Journal of Information Processing 27, 773-786, 2019",
        "num_citations": 7,
        "author_pub_id": "tRmAOagAAAAJ:UebtZRa9Y70C"
    },
    {
        "title": "A mechanism for prevention of flooding based ddos attack",
        "pub_year": "2017",
        "citation": "International Journal of Computational Intelligence Research 13 (1), 101-111, 2017",
        "num_citations": 36,
        "author_pub_id": "tRmAOagAAAAJ:MXK_kJrjxJIC"
    },
    {
        "title": "An Empirical Approach to Phishing Countermeasures through Smart Glasses and Validation Agents",
        "pub_year": "2019",
        "citation": "IEEE Access, 2019",
        "num_citations": 24,
        "author_pub_id": "tRmAOagAAAAJ:Tyk-4Ss8FVUC"
    },
    {
        "title": "An Empirical Approach to Phishing Countermeasures through Smart Glasses and Validation Agents",
        "citation": "",
        "num_citations": 0,
        "author_pub_id": "tRmAOagAAAAJ:hC7cP41nSMkC"
    },
    {
        "title": "Artificial intelligence-based smart grid vulnerabilities and potential solutions for fake-normal attacks: a short review",
        "pub_year": "2022",
        "citation": "arXiv preprint arXiv:2202.07050, 2022",
        "num_citations": 2,
        "author_pub_id": "tRmAOagAAAAJ:QIV2ME_5wuYC"
    },
    {
        "title": "Authentication of  Web-Server Traffic through Machine Learning for DDoS Attack Detection and Prevention",
        "pub_year": "2015",
        "citation": "Jawaharlal Nehru Technological University, 2015",
        "num_citations": 0,
        "author_pub_id": "tRmAOagAAAAJ:ULOm3_A8WrAC"
    },
    {
        "title": "Automatic Escaped Animal Detection and Monitoring System: A Case study of Volcanoes National Park (VNP) in Rwanda",
        "pub_year": "2022",
        "citation": "ijasre, 2022",
        "num_citations": 0,
        "author_pub_id": "tRmAOagAAAAJ:IWHjjKOFINEC"
    },
    {
        "title": "Classifying swahili smishing attacks for mobile money users: A machine-learning approach",
        "pub_year": "2022",
        "citation": "IEEE Access 10, 83061-83074, 2022",
        "num_citations": 19,
        "author_pub_id": "tRmAOagAAAAJ:ZeXyd9-uunAC"
    },
    {
        "title": "Detection of username enumeration attack on ssh protocol: Machine learning approach",
        "pub_year": "2021",
        "citation": "Symmetry 13 (11), 2192, 2021",
        "num_citations": 9,
        "author_pub_id": "tRmAOagAAAAJ:Wp0gIr-vW9MC"
    },
    {
        "title": "FakeAP Detector: An Android-Based Client-Side Application for Detecting Wi-Fi Hotspot Spoofing",
        "pub_year": "2022",
        "citation": "Ieee Access 10, 13611-13623, 2022",
        "num_citations": 2,
        "author_pub_id": "tRmAOagAAAAJ:mVmsd5A6BfQC"
    },
    {
        "title": "FakeAP Detector: An Android-Based Client-Side Application for Detecting Wi-Fi Hotspot Spoofing",
        "citation": "",
        "num_citations": 0,
        "author_pub_id": "tRmAOagAAAAJ:-f6ydRqryjwC"
    },
    {
        "title": "Investigating the Challenges Companies in Rwanda Face when Implementing Zero-Trust Network",
        "pub_year": "2023",
        "citation": "2023 10th International Conference on Future Internet of Things and Cloud …, 2023",
        "num_citations": 0,
        "author_pub_id": "tRmAOagAAAAJ:hFOr9nPyWt4C"
    },
    {
        "title": "Low time complexity model for email spam detection using logistic regression",
        "pub_year": "2021",
        "citation": "International Journal of Advanced Computer Science and Applications 12 (12), 2021",
        "num_citations": 5,
        "author_pub_id": "tRmAOagAAAAJ:7PzlFSSx8tAC"
    },
    {
        "title": "NATURAL LANGUAGE UNDERSTANDING FOR AFRICAN LANGUAGES",
        "pub_year": "2023",
        "citation": "4th Workshop on African Natural Language Processing, 2023",
        "num_citations": 2,
        "author_pub_id": "tRmAOagAAAAJ:qUcmZB5y_30C"
    },
    {
        "title": "Phishing Attack Detection by Deceptive Login Simulation through an Android Mobile App",
        "pub_year": "2017",
        "citation": "Asia Joint Conference on Information Securit, p2-11, 2017",
        "num_citations": 0,
        "author_pub_id": "tRmAOagAAAAJ:5nxA0vEk-isC"
    },
    {
        "title": "Recent attack prevention techniques in web service applications",
        "pub_year": "2016",
        "citation": "2016 International Conference on Automatic Control and Dynamic Optimization …, 2016",
        "num_citations": 24,
        "author_pub_id": "tRmAOagAAAAJ:Se3iqnhoufwC"
    },
    {
        "title": "Securing low-computational-power devices against ARP spoofing attacks through a lightweight android application",
        "pub_year": "2017",
        "citation": "2017 21st International Computer Science and Engineering Conference (ICSEC), 1-6, 2017",
        "num_citations": 3,
        "author_pub_id": "tRmAOagAAAAJ:UeHWp8X0CEIC"
    },
    {
        "title": "Security of Cryptocurrencies in blockchain technology: State-of-art, challenges and future prospects",
        "pub_year": "2020",
        "citation": "Journal of Network and Computer Applications 163, 102635, 2020",
        "num_citations": 210,
        "author_pub_id": "tRmAOagAAAAJ:4TOpqqG69KYC"
    },
    {
        "title": "Smart System for Controlling and Monitoring Water and Turbidity Levels in Dam Reservoir using Micro-Controller Technology",
        "pub_year": "2022",
        "citation": "Engineering, Technology & Applied Science Research, 2022",
        "num_citations": 0,
        "author_pub_id": "tRmAOagAAAAJ:L8Ckcad2t8MC"
    },
    {
        "title": "Smart4gap: Factors that influence smartphone security decisions in developing and developed countries",
        "pub_year": "2018",
        "citation": "Proceedings of the 2018 10th International Conference on Information …, 2018",
        "num_citations": 11,
        "author_pub_id": "tRmAOagAAAAJ:IjCSPb-OGe4C"
    },
    {
        "title": "Software-based computing platform as an experimental topology assembled to detect and mitigate DDoS attacks using virtual environments",
        "pub_year": "2016",
        "citation": "2016 International Symposium on Performance Evaluation of Computer and …, 2016",
        "num_citations": 6,
        "author_pub_id": "tRmAOagAAAAJ:8k81kl-MbHgC"
    },
    {
        "title": "To coerce or not to coerce? a quantitative investigation on cybersecurity and cybercrime legislations towards large-scale vulnerability notifications",
        "pub_year": "2019",
        "citation": "2019 IEEE International Symposium on Software Reliability Engineering …, 2019",
        "num_citations": 6,
        "author_pub_id": "tRmAOagAAAAJ:Zph67rFs4hoC"
    },
    {
        "title": "UnPhishMe: Phishing attack detection by deceptive login simulation through an Android mobile app",
        "pub_year": "2017",
        "citation": "2017 12th Asia Joint Conference on Information Security (AsiaJCIS), 38-47, 2017",
        "num_citations": 23,
        "author_pub_id": "tRmAOagAAAAJ:9yKSN-GCB0IC"
    },
    {
        "title": "Uncovering SMS Spam in Swahili Text Using Deep Learning Approaches",
        "pub_year": "2024",
        "citation": "IEEE Access, 2024",
        "num_citations": 1,
        "author_pub_id": "tRmAOagAAAAJ:mB3voiENLucC"
    },
    {
        "title": "Validation Agents and Persuasive Designs for Phishing Detection and Update Compliance on Smartphones",
        "pub_year": "2019",
        "citation": "奈良先端科学技術大学院大学, 2019",
        "num_citations": 0,
        "author_pub_id": "tRmAOagAAAAJ:0EnyYjriUFMC"
    },
    {
        "title": "Web Server protection against application layer DDoS attacks using machine learning and traffic authentication",
        "pub_year": "2015",
        "citation": "2015 IEEE 39th Annual Computer Software and Applications Conference 3, 261-267, 2015",
        "num_citations": 58,
        "author_pub_id": "tRmAOagAAAAJ:u-x6o8ySG0sC"
    }
]